pdfdancer/__init__.py
pdfdancer/exceptions.py
pdfdancer/fingerprint.py
pdfdancer/image_builder.py
pdfdancer/models.py
pdfdancer/page_builder.py
pdfdancer/paragraph_builder.py
pdfdancer/path_builder.py
pdfdancer/pdfdancer_v1.py
pdfdancer/text_line_builder.py
pdfdancer/types.py
pdfdancer_client_python-0.3.5.dist-info/licenses/LICENSE
pdfdancer_client_python-0.3.5.dist-info/licenses/NOTICE
pdfdancer_client_python-0.3.5.dist-info/METADATA
pdfdancer_client_python-0.3.5.dist-info/WHEEL
pdfdancer_client_python-0.3.5.dist-info/top_level.txt
pdfdancer_client_python-0.3.5.dist-info/RECORD
