Metadata-Version: 2.4
Name: pdfdancer-client-python
Version: 0.3.5
Summary: Python client for PDFDancer API
Author-email: "The Famous Cat Ltd." <hi@thefamouscat.com>
License: 
Project-URL: Homepage, https://www.pdfdancer.com/
Project-URL: Documentation, https://www.pdfdancer.com/
Project-URL: Source, https://github.com/MenschMachine/pdfdancer-client-python
Project-URL: Issues, https://github.com/MenschMachine/pdfdancer-client-python/issues
Classifier: Development Status :: 4 - Beta
Classifier: Intended Audience :: Developers
Classifier: License :: OSI Approved :: Apache Software License
Classifier: Programming Language :: Python :: 3.10
Classifier: Programming Language :: Python :: 3.11
Classifier: Programming Language :: Python :: 3.12
Classifier: Programming Language :: Python :: 3.13
Requires-Python: >=3.10
License-File: LICENSE
License-File: NOTICE
Requires-Dist: httpx[http2]>=0.27.0
Requires-Dist: pydantic>=1.8.0
Requires-Dist: typing-extensions>=4.0.0
Requires-Dist: python-dotenv>=0.19.0
Provides-Extra: dev
Requires-Dist: pytest>=7.0; extra == "dev"
Requires-Dist: pytest-cov>=4.0; extra == "dev"
Requires-Dist: pytest-mock>=3.10.0; extra == "dev"
Requires-Dist: black>=22.0; extra == "dev"
Requires-Dist: flake8>=5.0; extra == "dev"
Requires-Dist: mypy>=1.0; extra == "dev"
Requires-Dist: isort>=5.10.0; extra == "dev"
Requires-Dist: build>=0.8.0; extra == "dev"
Requires-Dist: twine>=4.0.0; extra == "dev"
Dynamic: license-file
